mtmaisdk/__init__.py
mtmaisdk/_version.py
mtmaisdk/client.py
mtmaisdk/connection.py
mtmaisdk/hatchet.py
mtmaisdk/labels.py
mtmaisdk/loader.py
mtmaisdk/logger.py
mtmaisdk/metadata.py
mtmaisdk/rate_limit.py
mtmaisdk/semver.py
mtmaisdk/token.py
mtmaisdk/workflow.py
mtmaisdk/workflow_run.py
mtmaisdk/clients/admin.py
mtmaisdk/clients/event_ts.py
mtmaisdk/clients/events.py
mtmaisdk/clients/mtmapi.py
mtmaisdk/clients/rest_client.py
mtmaisdk/clients/run_event_listener.py
mtmaisdk/clients/workflow_listener.py
mtmaisdk/clients/dispatcher/action_listener.py
mtmaisdk/clients/dispatcher/dispatcher.py
mtmaisdk/clients/rest/__init__.py
mtmaisdk/clients/rest/api_client.py
mtmaisdk/clients/rest/api_response.py
mtmaisdk/clients/rest/configuration.py
mtmaisdk/clients/rest/exceptions.py
mtmaisdk/clients/rest/rest.py
mtmaisdk/clients/rest/tenacity_utils.py
mtmaisdk/clients/rest/api/__init__.py
mtmaisdk/clients/rest/api/admin_api.py
mtmaisdk/clients/rest/api/agent_api.py
mtmaisdk/clients/rest/api/api_token_api.py
mtmaisdk/clients/rest/api/artifact_api.py
mtmaisdk/clients/rest/api/assisant_api.py
mtmaisdk/clients/rest/api/blog_api.py
mtmaisdk/clients/rest/api/chat_api.py
mtmaisdk/clients/rest/api/default_api.py
mtmaisdk/clients/rest/api/doc_api.py
mtmaisdk/clients/rest/api/event_api.py
mtmaisdk/clients/rest/api/frontend_api.py
mtmaisdk/clients/rest/api/github_api.py
mtmaisdk/clients/rest/api/healthcheck_api.py
mtmaisdk/clients/rest/api/llm_api.py
mtmaisdk/clients/rest/api/llmproxy_api.py
mtmaisdk/clients/rest/api/log_api.py
mtmaisdk/clients/rest/api/metadata_api.py
mtmaisdk/clients/rest/api/mtbizflow_api.py
mtmaisdk/clients/rest/api/mtmai_api.py
mtmaisdk/clients/rest/api/post_api.py
mtmaisdk/clients/rest/api/posts_api.py
mtmaisdk/clients/rest/api/prompt_api.py
mtmaisdk/clients/rest/api/rate_limits_api.py
mtmaisdk/clients/rest/api/site_api.py
mtmaisdk/clients/rest/api/slack_api.py
mtmaisdk/clients/rest/api/sns_api.py
mtmaisdk/clients/rest/api/step_run_api.py
mtmaisdk-0.5.56.dist-info/METADATA
mtmaisdk-0.5.56.dist-info/WHEEL
mtmaisdk-0.5.56.dist-info/RECORD
